[
  {
     "mal_id":569,
     "name":"MAPPA"
  },
  {
     "mal_id":2,
     "name":"Kyoto Animation"
  },
  {
     "mal_id":11,
     "name":"Madhouse"
  },
  {
     "mal_id":43,
     "name":"ufotable"
  },
  {
     "mal_id":858,
     "name":"Wit Studio"
  },
  {
     "mal_id":4,
     "name":"Bones"
  },
  {
     "mal_id":21,
     "name":"Studio Ghibli"
  },
  {
     "mal_id":56,
     "name":"A-1 Pictures"
  },
  {
     "mal_id":44,
     "name":"Shaft"
  },
  {
     "mal_id":1835,
     "name":"CloverWorks"
  },
  {
     "mal_id":803,
     "name":"Trigger"
  },
  {
     "mal_id":10,
     "name":"Production I.G"
  },
  {
     "mal_id":18,
     "name":"Toei Animation"
  },
  {
     "mal_id":14,
     "name":"Sunrise"
  },
  {
     "mal_id":287,
     "name":"David Production"
  },
  {
     "mal_id":314,
     "name":"White Fox"
  },
  {
     "mal_id":6,
     "name":"Gainax"
  },
  {
     "mal_id":1,
     "name":"Pierrot"
  },
  {
     "mal_id":7,
     "name":"J.C.Staff"
  },
  
  {
     "mal_id":132,
     "name":"P.A. Works"
  },
  
  {
     "mal_id":17,
     "name":"Aniplex"
  },
  {
     "mal_id":95,
     "name":"Doga Kobo"
  },
  {
     "mal_id":1591,
     "name":"Science SARU"
  },
  {
     "mal_id":1696,
     "name":"KADOKAWA"
  },
  {
     "mal_id":300,
     "name":"SILVER LINK."
  },
  {
     "mal_id":73,
     "name":"TMS Entertainment"
  },
  
  {
     "mal_id":28,
     "name":"OLM"
  },
  {
     "mal_id":456,
     "name":"Lerche"
  },
  
  {
     "mal_id":37,
     "name":"Studio Deen"
  },
  {
     "mal_id":2167,
     "name":"Hololive Production"
  },
  
  {
     "mal_id":112,
     "name":"Brain's Base"
  },
  
  {
     "mal_id":290,
     "name":"Kinema Citrus"
  },
  {
     "mal_id":441,
     "name":"8bit"
  },
  
  {
     "mal_id":91,
     "name":"feel."
  },
  
  {
     "mal_id":13,
     "name":"Studio 4°C"
  },
  {
     "mal_id":3,
     "name":"Gonzo"
  },
  {
     "mal_id":47,
     "name":"Khara"
  },
  {
     "mal_id":911,
     "name":"Passione"
  },
  {
     "mal_id":1258,
     "name":"Bandai Namco Pictures"
  },
  {
     "mal_id":839,
     "name":"LIDENFILMS"
  },
  {
     "mal_id":159,
     "name":"Kodansha"
  },
  {
     "mal_id":27,
     "name":"Xebec"
  },
  {
     "mal_id":555,
     "name":"Studio Chizu"
  },
  {
     "mal_id":120,
     "name":"TNK"
  },
  {
     "mal_id":1977,
     "name":"Netflix"
  },
  {
     "mal_id":439,
     "name":"Project No.9"
  },
  {
     "mal_id":103,
     "name":"Tatsunoko Production"
  },
  {
     "mal_id":48,
     "name":"AIC"
  },
  {
     "mal_id":1414,
     "name":"bilibili"
  },
  {
     "mal_id":65,
     "name":"Tokyo Movie Shinsha"
  },
  {
     "mal_id":541,
     "name":"Seven"
  },
  {
     "mal_id":2253,
     "name":"miHoYoAnime"
  },
  {
     "mal_id":418,
     "name":"Studio Gokumi"
  },
  {
     "mal_id":1203,
     "name":"Studio 1st"
  },
  {
     "mal_id":2674,
     "name":"BUG FILMS"
  },
  {
     "mal_id":2044,
     "name":"webtoon"
  },
  {
     "mal_id":245,
     "name":"TOHO"
  },
  {
     "mal_id":1393,
     "name":"Geno Studio"
  },
  {
     "mal_id":483,
     "name":"Marvel"
  },
  {
     "mal_id":1997,
     "name":"Studio Kai"
  },
  {
     "mal_id":144,
     "name":"Pony Canyon"
  },
  {
     "mal_id":2009,
     "name":"Yostar Pictures"
  },
  {
     "mal_id":783,
     "name":"GKIDS"
  },
  {
     "mal_id":51,
     "name":"Diomedéa"
  },
  {
     "mal_id":35,
     "name":"Seven Arcs"
  },
  {
     "mal_id":2067,
     "name":"Flat Studio"
  },
  {
     "mal_id":1075,
     "name":"C-Station"
  },
  {
     "mal_id":1325,
     "name":"Haoliners Animation League"
  },
  {
     "mal_id":68,
     "name":"Mushi Production"
  },
  {
     "mal_id":1893,
     "name":"CygamesPictures"
  },
  {
     "mal_id":1127,
     "name":"Studio 3Hz"
  }
]